sportsdata/__init__.py
sportsdata/apis/Api.py
sportsdata/apis/ApiNbaNet.py
sportsdata/apis/StatsNbaCom.py
sportsdata/apis/__init__.py
sportsdata/data/__init__.py
sportsdata/data/api.nba.net.json
sportsdata/data/stats-prod.nba.com.json
sportsdata/data/stats.nba.com.json
sportsdata/mlb/MLB.py
sportsdata/mlb/MLB2.py
sportsdata/mlb/__init__.py
sportsdata/mlb/handlers/BenchXml.py
sportsdata/mlb/handlers/BoxscoreXml.py
sportsdata/mlb/handlers/GameEventsXml.py
sportsdata/mlb/handlers/GameXml.py
sportsdata/mlb/handlers/GamedaySynXml.py
sportsdata/mlb/handlers/InningHit.py
sportsdata/mlb/handlers/InningHitXml.py
sportsdata/mlb/handlers/InningScoresXml.py
sportsdata/mlb/handlers/InningsAllXml.py
sportsdata/mlb/handlers/ScoreboardXml.py
sportsdata/mlb/handlers/__init__.py
sportsdata/models/AtBat.py
sportsdata/models/Bench.py
sportsdata/models/Boxscore.py
sportsdata/models/Bunch.py
sportsdata/models/Game.py
sportsdata/models/Inning.py
sportsdata/models/Scoreboard.py
sportsdata/models/__init__.py
sportsdata/nba/__init__.py
sportsdata/nba/boxscore.py
sportsdata/nba/constants.py
sportsdata/nba/league.py
sportsdata/nba/scoreboard.py
sportsdata/nba/season.py
sportsdata/nba/team.py
sportsdata/nba/teams.py
sportsdata/nba/seasons/__init__.py
sportsdata/nba/seasons/season_2000.py
sportsdata/nba/seasons/season_2001.py
sportsdata/nba/seasons/season_2002.py
sportsdata/nba/seasons/season_2003.py
sportsdata/nba/seasons/season_2004.py
sportsdata/nba/seasons/season_2005.py
sportsdata/nba/seasons/season_2006.py
sportsdata/nba/seasons/season_2007.py
sportsdata/nba/seasons/season_2008.py
sportsdata/nba/seasons/season_2009.py
sportsdata/nba/seasons/season_2010.py
sportsdata/nba/seasons/season_2011.py
sportsdata/nba/seasons/season_2012.py
sportsdata/nba/seasons/season_2013.py
sportsdata/nba/seasons/season_2014.py
sportsdata/nba/seasons/season_2015.py
sportsdata/nba/seasons/season_2016.py
sportsdata/nba/seasons/season_2017.py
sportsdata/nba/seasons/season_2018.py
sportsdata-0.0.46.dist-info/LICENSE
sportsdata-0.0.46.dist-info/METADATA
sportsdata-0.0.46.dist-info/WHEEL
sportsdata-0.0.46.dist-info/top_level.txt
sportsdata-0.0.46.dist-info/RECORD
