Metadata-Version: 2.1
Name: sportsdata
Version: 0.0.46
Summary: A collection of sports apis and higher level abstraction classes (Games, Season, Player, League, etc)
Home-page: https://opensource.fuzzybumblebee.org/sportsdata
Author: David Orkin
Author-email: david.orkin@fuzzybumblebee.org
License: UNKNOWN
Platform: UNKNOWN
Classifier: Programming Language :: Python :: 3
Classifier: License :: OSI Approved :: Apache Software License
Classifier: Operating System :: OS Independent
Requires-Python: >=3.6
License-File: LICENSE
Requires-Dist: pandas
